MANIFEST.in
README.txt
setup.py
django_appskel.egg-info/PKG-INFO
django_appskel.egg-info/SOURCES.txt
django_appskel.egg-info/dependency_links.txt
django_appskel.egg-info/not-zip-safe
django_appskel.egg-info/requires.txt
django_appskel.egg-info/top_level.txt
djangoappskel/__init__.py
djangoappskel/bin/django-appskel.py
djangoappskel/skel/MANIFEST.in
djangoappskel/skel/README.txt
djangoappskel/skel/coveragerc
djangoappskel/skel/requirements-12.txt
djangoappskel/skel/requirements-13.txt
djangoappskel/skel/requirements-trunk.txt
djangoappskel/skel/requirements.txt
djangoappskel/skel/runtests.sh
djangoappskel/skel/setup.py
djangoappskel/skel/.tx/config
djangoappskel/skel/__module__/__init__.py
djangoappskel/skel/__module__/admin.py
djangoappskel/skel/__module__/models.py
djangoappskel/skel/__module__/urls.py
djangoappskel/skel/__module__/views.py
djangoappskel/skel/__module__/locale/en/LC_MESSAGES/django.po
djangoappskel/skel/__module__/locale/en/LC_MESSAGES/djangojs.po
djangoappskel/skel/__module__/test/__init__.py
djangoappskel/skel/__module__/test/run_tests.py
djangoappskel/skel/__module__/test/testapp/__init__.py
djangoappskel/skel/__module__/test/testapp/models.py
djangoappskel/skel/__module__/test/testapp/urls.py
djangoappskel/skel/__module__/test/testapp/templates/__module__/__module___base.html
djangoappskel/skel/docs/Makefile
djangoappskel/skel/docs/conf.py
djangoappskel/skel/docs/contribution.rst
djangoappskel/skel/docs/index.rst