Metadata-Version: 1.0
Name: django-appskel
Version: 1.0a
Summary: App for building reusable app skeletons with testsr
Home-page: http://github.com/fivethreeo/django-appskel/
Author: Oyvind Saltvik
Author-email: oyvind.saltvik@gmail.com
License: UNKNOWN
Platform: UNKNOWN
Classifier: Development Status :: 4 - Beta
Classifier: Environment :: Web Environment
Classifier: Intended Audience :: Developers
Classifier: License :: OSI Approved :: BSD License
Classifier: Operating System :: OS Independent
Classifier: Programming Language :: Python
Classifier: Framework :: Django
